processcube_etw_library/__init__.py
processcube_etw_library/create_external_task_client.py
processcube_etw_library/etw_app.py
processcube_etw_library/identity_provider.py
processcube_etw_library/server_config.py
processcube_etw_library/settings.py
processcube_etw_library/typed_handler.py
processcube_etw_library/health/__init__.py
processcube_etw_library/health/built_in.py
processcube_etw_library/health/check.py
processcube_etw_library/health/handlers.py
processcube_etw_library/health/models.py
processcube_etw_library/health/registry.py
processcube_etw_library/health/routes.py
processcube_etw_library/processcube_client/__init__.py
processcube_etw_library/processcube_client/client_factory.py
processcube_etw_library/processcube_client/app_info/__init__.py
processcube_etw_library/processcube_client/app_info/app_info_client.py
processcube_etw_library/processcube_client/core/__init__.py
processcube_etw_library/processcube_client/core/base_client.py
processcube_etw_library/processcube_client/core/loop_helper.py
processcube_etw_library/processcube_client/core/api/__init__.py
processcube_etw_library/processcube_client/core/api/base_client.py
processcube_etw_library/processcube_client/core/api/client.py
processcube_etw_library/processcube_client/core/api/helpers/__init__.py
processcube_etw_library/processcube_client/core/api/helpers/application_info.py
processcube_etw_library/processcube_client/core/api/helpers/data_object_instances.py
processcube_etw_library/processcube_client/core/api/helpers/empty_tasks.py
processcube_etw_library/processcube_client/core/api/helpers/events.py
processcube_etw_library/processcube_client/core/api/helpers/external_tasks.py
processcube_etw_library/processcube_client/core/api/helpers/flow_node_instances.py
processcube_etw_library/processcube_client/core/api/helpers/manual_tasks.py
processcube_etw_library/processcube_client/core/api/helpers/process_definitions.py
processcube_etw_library/processcube_client/core/api/helpers/process_instances.py
processcube_etw_library-2026.1.30.154257.dist-info/METADATA
processcube_etw_library-2026.1.30.154257.dist-info/WHEEL
processcube_etw_library-2026.1.30.154257.dist-info/top_level.txt
processcube_etw_library-2026.1.30.154257.dist-info/RECORD
