Metadata-Version: 2.4
Name: processcube-etw-library
Version: 2026.1.30.154257
Summary: A library to create ETW apps with the ProcessCube platform.
Author-email: Jeremy Hill <jeremy.hill@profection.de>
License: MIT
Requires-Python: >=3.12
Requires-Dist: async-lru>=2.1.0
Requires-Dist: dataclasses-json>=0.6.7
Requires-Dist: fastapi[standard]>=0.128.0
Requires-Dist: oauth2-client>=1.4.2
Requires-Dist: tenacity>=9.1.2
